MANIFEST.in
setup.py
bin/pastalog
pastalog/__init__.py
pastalog/package.json
pastalog.egg-info/PKG-INFO
pastalog.egg-info/SOURCES.txt
pastalog.egg-info/dependency_links.txt
pastalog.egg-info/not-zip-safe
pastalog.egg-info/requires.txt
pastalog.egg-info/top_level.txt
pastalog/build/server.js
pastalog/build/assets/app.js