Metadata-Version: 1.0
Name: pastalog
Version: 1.0.3
Summary: Simple, realtime visualization of neural network training performance.
Home-page: http://github.com/rewonc/pastalog
Author: Rewon Child
Author-email: rewonc@gmail.com
License: MIT
Platform: UNKNOWN
